__init__.py
pyareas.py
pyareas-0.1.0.dist-info/LICENSE
pyareas-0.1.0.dist-info/METADATA
pyareas-0.1.0.dist-info/WHEEL
pyareas-0.1.0.dist-info/top_level.txt
pyareas-0.1.0.dist-info/RECORD
