Metadata-Version: 2.1
Name: pyareas
Version: 0.1.0
Summary: Python package for areas of 2D shapes
Author-email: TomTheCodingGuy <tomb80940@gmail.com>
Project-URL: Homepage, https://github.com/TomTheCodingGuy/pyareas
Project-URL: Bug Tracker, https://github.com/TomTheCodingGuy/pyareas/issues
Classifier: Programming Language :: Python :: 3
Classifier: License :: OSI Approved :: MIT License
Classifier: Operating System :: OS Independent
Requires-Python: >=3.7
License-File: LICENSE
